nivel2/decodificador/decodificador.v
module decodificador(input wire [3:0] Minutes, TenSec, Sec,
                     output reg [6:0] OutMinutes, OutTen, OutSec);
  
  always@(Minutes)
    case(Minutes)
      4'b0000 : OutMinutes = 7'b0000001;
      4'b0001 : OutMinutes = 7'b1001111;
      4'b0010 : OutMinutes = 7'b0010010;
      4'b0011 : OutMinutes = 7'b0000110;
      4'b0100 : OutMinutes = 7'b1001100;
      4'b0101 : OutMinutes = 7'b0100100;
      4'b0110 : OutMinutes = 7'b0100000;
      4'b0111 : OutMinutes = 7'b0001111;
      4'b1000 : OutMinutes = 7'b0000000;
      4'b1001 : OutMinutes = 7'b0000100;
    endcase

  always@(TenSec)
    case(TenSec)
      4'b0000 : OutTen = 7'b0000001;
      4'b0001 : OutTen = 7'b1001111;
      4'b0010 : OutTen = 7'b0010010;
      4'b0011 : OutTen = 7'b0000110;
      4'b0100 : OutTen = 7'b1001100;
      4'b0101 : OutTen = 7'b0100100;
      4'b0110 : OutTen = 7'b0100000;
      4'b0111 : OutTen = 7'b0001111;
      4'b1000 : OutTen = 7'b0000000;
      4'b1001 : OutTen = 7'b0000100;
    endcase
  
  always@(Sec)
    case(Sec)
      4'b0000 : OutSec = 7'b0000001;
      4'b0001 : OutSec = 7'b1001111;
      4'b0010 : OutSec = 7'b0010010;
      4'b0011 : OutSec = 7'b0000110;
      4'b0100 : OutSec = 7'b1001100;
      4'b0101 : OutSec = 7'b0100100;
      4'b0110 : OutSec = 7'b0100000;
      4'b0111 : OutSec = 7'b0001111;
      4'b1000 : OutSec = 7'b0000000;
      4'b1001 : OutSec = 7'b0000100;
    endcase
  
endmodule

nivel2/decodificador/testbench.v
`timescale 1ns/1ns
`include "decodificador.v"

module decodificador_teste;

    reg [3:0] Minutes_teste, TenSec_teste, Sec_teste;
  	wire [6:0] OutMinutes_teste, OutDezena_TB, OutSec_teste;

  	decodificador DUT(.Minutes(Minutes_teste), .TenSec(TenSec_teste), .Sec(Sec_teste), .OutMinutes(OutMinutes_teste), .OutTen(OutDezena_TB), .OutSec(OutSec_teste));

    initial
        begin
            $dumpfile("result.vcd");
            $dumpvars(0, decodificador_teste);

            Minutes_teste=4'b0000; TenSec_teste=4'b0000; Sec_teste=4'b0000;  
            #10  Minutes_teste=4'b0001; TenSec_teste=4'b0001; Sec_teste=4'b0001; 
         	  #10  Minutes_teste=4'b0010; TenSec_teste=4'b0010; Sec_teste=4'b0010;
            #10  Minutes_teste=4'b0011; TenSec_teste=4'b0011; Sec_teste=4'b0011;
            #10  Minutes_teste=4'b0100; TenSec_teste=4'b0100; Sec_teste=4'b0100;
            #10  Minutes_teste=4'b0101; TenSec_teste=4'b0101; Sec_teste=4'b0101;
          	#10  Minutes_teste=4'b0110; TenSec_teste=4'b0110; Sec_teste=4'b0110;
            #10  Minutes_teste=4'b0111; TenSec_teste=4'b0111; Sec_teste=4'b0111;
          	#10  Minutes_teste=4'b1000; TenSec_teste=4'b1000; Sec_teste=4'b1000;
            #10  Minutes_teste=4'b1001; TenSec_teste=4'b1001; Sec_teste=4'b1001;    
        end
endmodule

nivel2/decodificador/result.vcd
$date
	Sun Sep 24 19:59:53 2023
$end
$version
	Icarus Verilog
$end
$timescale
	1ns
$end
$scope module decodificador_teste $end
$var wire 7 ! OutSec_teste [6:0] $end
$var wire 7 " OutMinutes_teste [6:0] $end
$var wire 7 # OutDezena_TB [6:0] $end
$var reg 4 $ Minutes_teste [3:0] $end
$var reg 4 % Sec_teste [3:0] $end
$var reg 4 & TenSec_teste [3:0] $end
$scope module DUT $end
$var wire 4 ' Minutes [3:0] $end
$var wire 4 ( Sec [3:0] $end
$var wire 4 ) TenSec [3:0] $end
$var reg 7 * OutMinutes [6:0] $end
$var reg 7 + OutSec [6:0] $end
$var reg 7 , OutTen [6:0] $end
$upscope $end
$upscope $end
$enddefinitions $end
$comment Show the parameter values. $end
$dumpall
$end
#0
$dumpvars
b1 ,
b1 +
b1 *
b0 )
b0 (
b0 '
b0 &
b0 %
b0 $
b1 #
b1 "
b1 !
$end
#10
b1001111 !
b1001111 +
b1001111 #
b1001111 ,
b1001111 "
b1001111 *
b1 %
b1 (
b1 &
b1 )
b1 $
b1 '
#20
b10010 !
b10010 +
b10010 #
b10010 ,
b10010 "
b10010 *
b10 %
b10 (
b10 &
b10 )
b10 $
b10 '
#30
b110 !
b110 +
b110 #
b110 ,
b110 "
b110 *
b11 %
b11 (
b11 &
b11 )
b11 $
b11 '
#40
b1001100 !
b1001100 +
b1001100 #
b1001100 ,
b1001100 "
b1001100 *
b100 %
b100 (
b100 &
b100 )
b100 $
b100 '
#50
b100100 !
b100100 +
b100100 #
b100100 ,
b100100 "
b100100 *
b101 %
b101 (
b101 &
b101 )
b101 $
b101 '
#60
b100000 !
b100000 +
b100000 #
b100000 ,
b100000 "
b100000 *
b110 %
b110 (
b110 &
b110 )
b110 $
b110 '
#70
b1111 !
b1111 +
b1111 #
b1111 ,
b1111 "
b1111 *
b111 %
b111 (
b111 &
b111 )
b111 $
b111 '
#80
b0 !
b0 +
b0 #
b0 ,
b0 "
b0 *
b1000 %
b1000 (
b1000 &
b1000 )
b1000 $
b1000 '
#90
b100 !
b100 +
b100 #
b100 ,
b100 "
b100 *
b1001 %
b1001 (
b1001 &
b1001 )
b1001 $
b1001 '
